Cvsmerge/__init__.py
Cvsmerge/cvsmerge.py
cvsmergePack/__init__.py
cvsmergePack/cvsmerge.py
cvsmerge_py-2.0.0.dist-info/METADATA
cvsmerge_py-2.0.0.dist-info/WHEEL
cvsmerge_py-2.0.0.dist-info/top_level.txt
cvsmerge_py-2.0.0.dist-info/RECORD
