Metadata-Version: 2.1
Name: cvsmerge-py
Version: 2.0.0
Summary: module permettant de fusionner les data de deux fichier csv vers un seul fichier csv
Home-page: https://github.com/SadlieRose/Cvsmerge-_python_module.git
Author: Sadlie Rose Indiana Nazaire et Adelson Polycarpe
Author-email: nazairesadlierose@gmail.com
Classifier: Programming Language :: Python :: 3
Classifier: License :: OSI Approved :: MIT License
Classifier: Operating System :: OS Independent
Requires-Python: >=3.6
